setup.py
proxyhunter/__init__.py
proxyhunter/huntingOn.py
proxyhunter.egg-info/PKG-INFO
proxyhunter.egg-info/SOURCES.txt
proxyhunter.egg-info/dependency_links.txt
proxyhunter.egg-info/requires.txt
proxyhunter.egg-info/top_level.txt